[{"name":"2nd Kato Mylos","lat":34.895017,"lng":33.003524},{"name":"1st Kato Mylos","lat":34.89527,"lng":33.004739},{"name":"Kato Mylos Community Board 2","lat":34.894494,"lng":33.006611},{"name":"Agros - Lemesos Road - 3rd Kato Mylos","lat":34.893205,"lng":33.0073},{"name":"Agios Ioannis Elementary School","lat":34.89627,"lng":33.018431},{"name":"Petrou Iliadi Ave. 1","lat":34.913628,"lng":33.023285},{"name":"Christoforou Pissaridi Ave. - Agros","lat":34.915621,"lng":33.021654},{"name":"C.A.P.O. Agros Office 1","lat":34.917289,"lng":33.022049},{"name":"Agros Post Office 1","lat":34.916442,"lng":33.019618},{"name":"Panagia Eleousa Church 1","lat":34.917154,"lng":33.017713},{"name":"Apeitios School - Glafkos Clerides Sport Centre 1","lat":34.916091,"lng":33.014703},{"name":"Agridia","lat":34.927968,"lng":32.995128},{"name":"Chandria Square 2","lat":34.941918,"lng":32.993802},{"name":"Georgiou Griva Digeni Ave. - 2nd Chandria 1","lat":34.943532,"lng":32.993605},{"name":"Georgiou Griva Digeni Ave. - 3rd Chandria 1","lat":34.944487,"lng":32.990034},{"name":"Kyperounda Winery 1","lat":34.944414,"lng":32.981919},{"name":"Archiep. Makariou C´ Ave. - 7th Kyperounta 2","lat":34.941337,"lng":32.96821},{"name":"Archiep. Makariou C´ Ave. - 9th Kyperounta 1","lat":34.941993,"lng":32.961157},{"name":"Archiep. Makariou C´ Ave. - 10th Kyperounta 1","lat":34.94861,"lng":32.955262},{"name":"Kyperounta Hospital","lat":34.950619,"lng":32.952435}]