[{"name":"Tamasos Bus Station","lat":35.043261,"lng":33.189916},{"name":"B´  Regional High School Nicosia - Malounta","lat":35.045125,"lng":33.185282},{"name":"Griva Digeni-Leoforos Dimokratias","lat":35.045573,"lng":33.181665},{"name":"Klirou Military Camp","lat":35.026763,"lng":33.161935},{"name":"Agios Epifanios - Klirou Road 3","lat":35.010269,"lng":33.149123},{"name":"Agios Epifanios - Klirou Road 2","lat":34.99691,"lng":33.137121},{"name":"Agios Epifanios - Klirou Road","lat":34.995453,"lng":33.134248},{"name":"1st Agios Epifanios","lat":34.996497,"lng":33.127357},{"name":"Makariou C´ Ave. - 2nd Agios Epifanios","lat":34.996899,"lng":33.121955},{"name":"Makariou C´ Ave. - 3rd Agios Epifanios","lat":34.996873,"lng":33.121363},{"name":"Makariou C´ Ave. - 4th Agios Epifanios","lat":34.995945,"lng":33.120353},{"name":"Agios Epifanios Community Board","lat":34.995007,"lng":33.120155},{"name":"5th Agios Epifanios","lat":34.995743,"lng":33.132802},{"name":"4th Kykkou Nikiforou Ave.","lat":34.974836,"lng":33.128725},{"name":"3rd Kykkou Nikiforou Ave.","lat":34.965222,"lng":33.129685},{"name":"2nd Kykkou Nikiforou Ave.","lat":34.961437,"lng":33.127806},{"name":"1st Kykkou Nikiforou Ave.","lat":34.940747,"lng":33.12197},{"name":"Apliki","lat":34.931337,"lng":33.117828},{"name":"Anthoupoleos - Palaichoriou","lat":34.927508,"lng":33.103885},{"name":"Polykarpou Giorkatzi","lat":34.925395,"lng":33.097094},{"name":"Polykarpou - Giorgatzi 2","lat":34.924577,"lng":33.093688},{"name":"Palaichori Square","lat":34.922756,"lng":33.093182},{"name":"Agios Loucas Church 2","lat":34.921215,"lng":33.092009},{"name":"Agios Loucas Church","lat":34.922415,"lng":33.090434},{"name":"Palaichori Health Centre 2","lat":34.923858,"lng":33.091158},{"name":"Palaichori Health Centre","lat":34.924958,"lng":33.09106},{"name":"Palaichori - Askas Road","lat":34.927792,"lng":33.087264},{"name":"Askas","lat":34.929702,"lng":33.077259},{"name":"Fterikoudi 2","lat":34.941222,"lng":33.069626},{"name":"Fterikoudi","lat":34.942475,"lng":33.069561}]