[{"name":"Tamasos Bus Station","lat":35.043261,"lng":33.189916},{"name":"Ave. Archiepiskopou Makariou C - Eleftherias 2","lat":35.044798,"lng":33.193121},{"name":"Arediou Elementary School 2","lat":35.048715,"lng":33.196485},{"name":"Ave. Archiepiskopou Makariou C - Tamasou","lat":35.051854,"lng":33.201},{"name":"Georgiou Griva Digeni - Arediou Bakery","lat":35.053969,"lng":33.203417},{"name":"Lefkosia-Palaichori Road - Ergates Ind. Area 2","lat":35.068895,"lng":33.227661},{"name":"Archiep Makariou C - Ergates Industrial Area","lat":35.069027,"lng":33.229339},{"name":"Archiepiskopou Makariou C - Protomagias","lat":35.070285,"lng":33.241067},{"name":"Archiepiskopou Makariou C - Michail Karaoli","lat":35.074427,"lng":33.248462},{"name":"Archiepiskopou Makariou C - Athinas","lat":35.075364,"lng":33.25294},{"name":"Archiep. Makariou C - Missing Persons Monument ","lat":35.075965,"lng":33.254894},{"name":"Ave. Archiepiskopou Makariou C - Faneromenis","lat":35.077801,"lng":33.260439},{"name":"Ave. Archiep. Makariou C - Galaktika Supermarket","lat":35.07867,"lng":33.263239},{"name":"Ave. Archiepiskopou Makariou C - Omonoias","lat":35.081061,"lng":33.266856},{"name":"Ave. Archiepiskopou Makariou C - Eleftherias 2","lat":35.082731,"lng":33.269724},{"name":"Deftera Community Board","lat":35.084193,"lng":33.273513},{"name":"Ave. Archiepiskopou Makariou C - Iroon","lat":35.084829,"lng":33.275359},{"name":"Ave. Archiep. Makariou C - Chrysospiliotissis","lat":35.086137,"lng":33.279203},{"name":"Ave. Archiep. Makariou C - Anastasi Leventi","lat":35.086978,"lng":33.282014},{"name":"Ave. Archiepiskopou Makariou C - Foti Pitta","lat":35.088945,"lng":33.285421},{"name":"Ave. Archiepiskopou Makariou C - Strakka Area 2","lat":35.092837,"lng":33.290548},{"name":"Ave. Archiepiskopou Makariou C - Strakka Lake 2","lat":35.095571,"lng":33.293563},{"name":"Ave. Archiepiskopou Makariou C - Florinis","lat":35.0979,"lng":33.296139},{"name":"Ave. Archiepiskopou Makariou C - Profiti Ilia","lat":35.101289,"lng":33.300299},{"name":"Ave. Archiep. Makariou C - Archiep. Kyprianou","lat":35.104367,"lng":33.302768},{"name":"Ave. Archiepiskopou Makariou C - Agiou Georgiou","lat":35.108133,"lng":33.303967},{"name":"Elementary School A Lakatameia - Agia Paraskevi 2","lat":35.109717,"lng":33.305224},{"name":"Ave. Archiepiskopou Makariou C - Irakleous","lat":35.11259,"lng":33.306771},{"name":"Ave. Archiep. Makariou C - Nikou Alexandrou","lat":35.114362,"lng":33.308369},{"name":"Ave. Archiep. Makariou C - Archangelou Michail","lat":35.11687,"lng":33.311638},{"name":"Ave. Archiepiskopou Makariou C - Antheon","lat":35.120281,"lng":33.317292},{"name":"Ave. Archiepiskopou Makariou C - Voufavento","lat":35.122375,"lng":33.319989},{"name":"Ave. Strovolou - Averkiou","lat":35.124858,"lng":33.322303},{"name":"Ave. Strovolou - Lakatameia Roundabout  2","lat":35.127775,"lng":33.32417},{"name":"Ave. Strovolou - Zografou","lat":35.131626,"lng":33.327115},{"name":"Ave. Strovolou - PEPSI","lat":35.134323,"lng":33.33009},{"name":"Public Works Department 2","lat":35.138128,"lng":33.333508},{"name":"Ave. Strovolou - Ilia Venezi","lat":35.140811,"lng":33.338196},{"name":"Strovolos City Hall 2","lat":35.143333,"lng":33.342465},{"name":"Ave. Athalassas - 28 Oktovriou","lat":35.149635,"lng":33.348958},{"name":"Ave. Athalassas - Adamantiou Korai","lat":35.148818,"lng":33.351052},{"name":"Ave. Athalassas - Ious","lat":35.147509,"lng":33.354625},{"name":"Ave. Athalassas - Nicosia Water Board 2","lat":35.146418,"lng":33.357551},{"name":"Ave. Georgiou Paraskevaidi - Akropolis Park 2","lat":35.146375,"lng":33.359977},{"name":"Ave. Akropoleos - Kypragorou","lat":35.149396,"lng":33.359859},{"name":"Bank of Cyprus Oncology Center 2","lat":35.152997,"lng":33.358876},{"name":"Nikis - Kasou","lat":35.156445,"lng":33.357727},{"name":"Nikis - Samou","lat":35.15978,"lng":33.358005},{"name":"Ave. Kyriakou Matsi - Georgiou Griva Digeni Avenue","lat":35.162358,"lng":33.358587},{"name":"Ave. Georgiou Griva Digeni - Iasonos","lat":35.162994,"lng":33.356855},{"name":"Ave. Dimostheni Severi - Ministry of Interior","lat":35.165264,"lng":33.354427},{"name":"Ministry of Finance","lat":35.168626,"lng":33.354947},{"name":"Solomos Square Alighting ","lat":35.170392,"lng":33.358392}]