[
  {
    "description": "Pano Kyvides - Agios Amvrosios Road",
    "lat": 34.7770141743223,
    "lon": 32.8326093819059,
    "name": "Pano Kyvides - Agios Amvrosios Road"
  },
  {
    "description": "1st Vouni",
    "lat": 34.8247310851315,
    "lon": 32.8356404304067,
    "name": "1st Vouni"
  },
  {
    "description": "2nd Vouni",
    "lat": 34.8202820714615,
    "lon": 32.8332217342894,
    "name": "2nd Vouni"
  },
  {
    "description": "Agios Efraim Church 2",
    "lat": 34.7834457999143,
    "lon": 32.8275576740004,
    "name": "Agios Efraim Church 2"
  }
]